educelab/tei/__init__.py
educelab/tei/constants.py
educelab/tei/exceptions.py
educelab/tei/file_desc.py
educelab/tei/profile_desc.py
educelab/tei/tei.py
educelab/tei/utils.py
educelab/tei/schemas/tei_schema.xsd
educelab_tei-0.1.1.dist-info/LICENSE
educelab_tei-0.1.1.dist-info/METADATA
educelab_tei-0.1.1.dist-info/WHEEL
educelab_tei-0.1.1.dist-info/top_level.txt
educelab_tei-0.1.1.dist-info/RECORD
