Metadata-Version: 2.1
Name: educelab-tei
Version: 0.1.1
Summary: EduceLab TEI profile library and tools
Home-page: https://gitlab.com/educelab/educelab-tei
Author: Seth Parker
Author-email: c.seth.parker@uky.edu
Classifier: Programming Language :: Python :: 3
Classifier: Programming Language :: Python :: 3.9
Classifier: Programming Language :: Python :: 3.10
Classifier: Operating System :: OS Independent
Requires-Python: >=3.9
License-File: LICENSE
Requires-Dist: lxml
